flwr_tune/__init__.py
flwr_tune-0.0.1.dist-info/METADATA
flwr_tune-0.0.1.dist-info/WHEEL
flwr_tune-0.0.1.dist-info/RECORD
